transitmaplint/__init__.py
transitmaplint/main.py
transitmaplint/prompts.py
transitmaplint-2025.12.21125921.dist-info/METADATA
transitmaplint-2025.12.21125921.dist-info/WHEEL
transitmaplint-2025.12.21125921.dist-info/top_level.txt
transitmaplint-2025.12.21125921.dist-info/RECORD
