Metadata-Version: 2.4
Name: transitmaplint
Version: 2025.12.21125921
Summary: A new package that takes user-provided text descriptions of transportation or infrastructure maps (like train networks) and returns structured feedback or improvements. It analyzes the input for key e
Author-email: transitmaplint <hi@eugene.plus>
License: MIT
Project-URL: Homepage, https://github.com/chigwell/transitmaplint
Requires-Python: >=3.9
Requires-Dist: langchain-llm7>=0.0.0
Requires-Dist: llmatch-messages>=0.0.0
Requires-Dist: langchain-core>=0.3.0
